// class version 50.0 (50)
// access flags 0x401
public abstract class TFrame$$PassThrough$class {


  // access flags 0x9
  public static $init$(LTFrame$$PassThrough;)V
    RETURN
    MAXSTACK = 1
    MAXLOCALS = 1

  // access flags 0x9
  public static bindPart(LTFrame$$PassThrough;Lcodechicken/multipart/TMultiPart;)V
    ALOAD 0
    ALOAD 1
    INVOKEINTERFACE TFrame$$PassThrough.TFrame$$PassThrough$$super$bindPart (Lcodechicken/multipart/TMultiPart;)V
    ALOAD 1
    INSTANCEOF mrtjp/mcframes/api/IFrame
    IFEQ L0
    ALOAD 0
    ALOAD 1
    CHECKCAST mrtjp/mcframes/api/IFrame
    INVOKEINTERFACE TFrame$$PassThrough.TFrame$$PassThrough$$impl_$eq (Lmrtjp/mcframes/api/IFrame;)V
   L0
   FRAME FULL [TFrame$$PassThrough codechicken/multipart/TMultiPart] []
    RETURN
    MAXSTACK = 2
    MAXLOCALS = 2

  // access flags 0x9
  public static partRemoved(LTFrame$$PassThrough;Lcodechicken/multipart/TMultiPart;I)V
    ALOAD 0
    ALOAD 1
    ILOAD 2
    INVOKEINTERFACE TFrame$$PassThrough.TFrame$$PassThrough$$super$partRemoved (Lcodechicken/multipart/TMultiPart;I)V
    ALOAD 1
    ALOAD 0
    INVOKEINTERFACE TFrame$$PassThrough.TFrame$$PassThrough$$impl ()Lmrtjp/mcframes/api/IFrame;
    IF_ACMPNE L0
    ALOAD 0
    ACONST_NULL
    INVOKEINTERFACE TFrame$$PassThrough.TFrame$$PassThrough$$impl_$eq (Lmrtjp/mcframes/api/IFrame;)V
   L0
   FRAME FULL [TFrame$$PassThrough codechicken/multipart/TMultiPart I] []
    RETURN
    MAXSTACK = 3
    MAXLOCALS = 3

  // access flags 0x9
  public static canAddPart(LTFrame$$PassThrough;Lcodechicken/multipart/TMultiPart;)Z
    ALOAD 0
    INVOKEINTERFACE TFrame$$PassThrough.TFrame$$PassThrough$$impl ()Lmrtjp/mcframes/api/IFrame;
    IFNULL L0
    ALOAD 1
    INSTANCEOF mrtjp/mcframes/api/IFrame
    IFEQ L0
    ICONST_0
    IRETURN
   L0
   FRAME FULL [TFrame$$PassThrough codechicken/multipart/TMultiPart] []
    ALOAD 0
    ALOAD 1
    INVOKEINTERFACE TFrame$$PassThrough.TFrame$$PassThrough$$super$canAddPart (Lcodechicken/multipart/TMultiPart;)Z
    IRETURN
    MAXSTACK = 2
    MAXLOCALS = 2

  // access flags 0x9
  public static stickOut(LTFrame$$PassThrough;Lnet/minecraft/world/World;IIII)Z
    ALOAD 0
    INVOKEINTERFACE TFrame$$PassThrough.TFrame$$PassThrough$$impl ()Lmrtjp/mcframes/api/IFrame;
    ALOAD 1
    ILOAD 2
    ILOAD 3
    ILOAD 4
    ILOAD 5
    INVOKEINTERFACE mrtjp/mcframes/api/IFrame.stickOut (Lnet/minecraft/world/World;IIII)Z
    IRETURN
    MAXSTACK = 6
    MAXLOCALS = 6

  // access flags 0x9
  public static stickIn(LTFrame$$PassThrough;Lnet/minecraft/world/World;IIII)Z
    ALOAD 0
    INVOKEINTERFACE TFrame$$PassThrough.TFrame$$PassThrough$$impl ()Lmrtjp/mcframes/api/IFrame;
    ALOAD 1
    ILOAD 2
    ILOAD 3
    ILOAD 4
    ILOAD 5
    INVOKEINTERFACE mrtjp/mcframes/api/IFrame.stickIn (Lnet/minecraft/world/World;IIII)Z
    IRETURN
    MAXSTACK = 6
    MAXLOCALS = 6

  // access flags 0x9
  public static copyFrom(LTFrame$$PassThrough;Lcodechicken/multipart/TileMultipart;)V
    ALOAD 0
    ALOAD 1
    INVOKEINTERFACE TFrame$$PassThrough.TFrame$$PassThrough$$super$copyFrom (Lcodechicken/multipart/TileMultipart;)V
    ALOAD 1
    INSTANCEOF TFrame$$PassThrough
    IFEQ L0
    ALOAD 0
    ALOAD 1
    INVOKEINTERFACE TFrame$$PassThrough.TFrame$$PassThrough$$impl ()Lmrtjp/mcframes/api/IFrame;
    INVOKEINTERFACE TFrame$$PassThrough.TFrame$$PassThrough$$impl_$eq (Lmrtjp/mcframes/api/IFrame;)V
   L0
    RETURN
    MAXSTACK = 2
    MAXLOCALS = 2
}
